odoo/addons/sale_invoice_policy/README.rst
odoo/addons/sale_invoice_policy/__init__.py
odoo/addons/sale_invoice_policy/__manifest__.py
odoo/addons/sale_invoice_policy/hooks.py
odoo/addons/sale_invoice_policy/i18n/ca.po
odoo/addons/sale_invoice_policy/i18n/es.po
odoo/addons/sale_invoice_policy/i18n/es_MX.po
odoo/addons/sale_invoice_policy/i18n/fr.po
odoo/addons/sale_invoice_policy/i18n/it.po
odoo/addons/sale_invoice_policy/i18n/pt.po
odoo/addons/sale_invoice_policy/i18n/sale_invoice_policy.pot
odoo/addons/sale_invoice_policy/models/__init__.py
odoo/addons/sale_invoice_policy/models/res_company.py
odoo/addons/sale_invoice_policy/models/res_config_settings.py
odoo/addons/sale_invoice_policy/models/sale_order.py
odoo/addons/sale_invoice_policy/models/sale_order_line.py
odoo/addons/sale_invoice_policy/readme/CONFIGURE.md
odoo/addons/sale_invoice_policy/readme/CONTEXT.md
odoo/addons/sale_invoice_policy/readme/CONTRIBUTORS.md
odoo/addons/sale_invoice_policy/readme/DESCRIPTION.md
odoo/addons/sale_invoice_policy/readme/USAGE.md
odoo/addons/sale_invoice_policy/static/description/icon.png
odoo/addons/sale_invoice_policy/static/description/index.html
odoo/addons/sale_invoice_policy/tests/__init__.py
odoo/addons/sale_invoice_policy/tests/test_sale_invoice_policy.py
odoo/addons/sale_invoice_policy/views/res_config_settings_view.xml
odoo/addons/sale_invoice_policy/views/sale_view.xml
odoo_addon_sale_invoice_policy-18.0.1.1.0.dist-info/METADATA
odoo_addon_sale_invoice_policy-18.0.1.1.0.dist-info/WHEEL
odoo_addon_sale_invoice_policy-18.0.1.1.0.dist-info/top_level.txt
odoo_addon_sale_invoice_policy-18.0.1.1.0.dist-info/RECORD
