Metadata-Version: 2.1
Name: odoo-addon-sale_invoice_policy
Version: 18.0.1.1.0
Requires-Python: >=3.10
Requires-Dist: odoo-addon-base_partition==18.0.*
Requires-Dist: odoo==18.0.*
Requires-Dist: openupgradelib
Summary: Sales Management: let the user choose the invoice policy on the order
Home-page: https://github.com/OCA/sale-workflow
License: AGPL-3
Author: ACSONE SA/NV, Odoo Community Association (OCA)
Author-email: support@odoo-community.org
Classifier: Programming Language :: Python
Classifier: Framework :: Odoo
Classifier: Framework :: Odoo :: 18.0
Classifier: License :: OSI Approved :: GNU Affero General Public License v3
